data_memory/data_memory/DataMemory.v

module DataMemory #(
    parameter DATA_WIDTH = 32,      // Độ rộng dữ liệu (mặc định 32-bit)
    parameter MEM_ADDR_WIDTH = 10   // Độ rộng địa chỉ (ví dụ 10 bit = 1024 từ nhớ)
)(
    input wire clk,
    input wire reset,               // Reset đồng bộ
    
    input wire mem_read_en,         // Tín hiệu cho phép đọc
    input wire mem_write_en,        // Tín hiệu cho phép ghi
    
    input wire [MEM_ADDR_WIDTH-1:0] mem_address, // Địa chỉ bộ nhớ
    input wire [DATA_WIDTH-1:0]     write_data,  // Dữ liệu cần ghi
    
    output reg [DATA_WIDTH-1:0]     read_data    // Dữ liệu đọc ra
);

    // 1. Khai báo mảng bộ nhớ (RAM)
    // Kích thước mảng là 2^MEM_ADDR_WIDTH
    localparam MEM_SIZE = 1 << MEM_ADDR_WIDTH;
    reg [DATA_WIDTH-1:0] mem [0:MEM_SIZE-1];

    integer i; // Biến dùng cho vòng lặp reset

    // 2. Logic Đọc (Read Logic)
    // Sử dụng logic tổ hợp (always @* hoặc assign) để dữ liệu có ngay trong chu kỳ
    // Nếu mem_read_en = 1 thì đọc từ mem, ngược lại trả về 0 (hoặc giữ nguyên tùy thiết kế)
    always @(*) begin
        if (mem_read_en) begin
            read_data = mem[mem_address];
        end else begin
            read_data = {DATA_WIDTH{1'b0}};
        end
    end

    // 3. Logic Ghi và Reset (Write & Reset Logic) - Tuần tự (Sequential)
    always @(posedge clk) begin
        if (reset) begin
            // Reset đồng bộ: Xóa toàn bộ bộ nhớ (chỉ nên dùng trong mô phỏng/FPGA nhỏ)
            // Trong thực tế ASIC, RAM hiếm khi có reset toàn bộ.
            for (i = 0; i < MEM_SIZE; i = i + 1) begin
                mem[i] <= {DATA_WIDTH{1'b0}};
            end
        end 
        else if (mem_write_en) begin
            // Chỉ ghi khi tín hiệu cho phép ghi bật
            mem[mem_address] <= write_data;
        end
    end

endmodule

data_memory/data_memory/DataMemory_tb.v

`timescale 1ns / 1ps

module DataMemory_tb;

    // Parameters
    parameter DATA_WIDTH = 32;
    parameter MEM_ADDR_WIDTH = 10;

    // Inputs
    reg clk;
    reg reset;
    reg mem_read_en;
    reg mem_write_en;
    reg [MEM_ADDR_WIDTH-1:0] mem_address;
    reg [DATA_WIDTH-1:0] write_data;

    // Outputs
    wire [DATA_WIDTH-1:0] read_data;

    // Instantiate the Unit Under Test (UUT)
    DataMemory #(
        .DATA_WIDTH(DATA_WIDTH),
        .MEM_ADDR_WIDTH(MEM_ADDR_WIDTH)
    ) uut (
        .clk(clk),
        .reset(reset),
        .mem_read_en(mem_read_en),
        .mem_write_en(mem_write_en),
        .mem_address(mem_address),
        .write_data(write_data),
        .read_data(read_data)
    );

    // Clock generation
    initial begin
        clk = 0;
        forever #5 clk = ~clk; // Chu kỳ 10ns
    end

    // Test sequence
    initial begin
        // Setup GTKWave (Trang 8)
        $dumpfile("DataMemory_tb.vcd");
        $dumpvars(0, DataMemory_tb);

        // 1. Khởi tạo
        reset = 1;
        mem_read_en = 0;
        mem_write_en = 0;
        mem_address = 0;
        write_data = 0;
        #15; // Đợi qua cạnh lên clk để reset
        
        reset = 0;
        $display("--- Bat dau Test ---");

        // 2. Test Ghi (Write)
        // Ghi giá trị 100 vào địa chỉ 5
        #10;
        mem_address = 5;
        write_data = 32'd100;
        mem_write_en = 1;
        mem_read_en = 0;
        #10; // Đợi 1 chu kỳ clock để ghi xong
        mem_write_en = 0; // Tắt ghi

        // Ghi giá trị 255 vào địa chỉ 10
        mem_address = 10;
        write_data = 32'd255;
        mem_write_en = 1;
        #10;
        mem_write_en = 0;

        // 3. Test Đọc (Read)
        // Đọc lại địa chỉ 5
        mem_address = 5;
        mem_read_en = 1;
        #5; 
        if (read_data == 32'd100) 
            $display("[PASS] Doc dia chi 5: %d", read_data);
        else 
            $display("[FAIL] Doc dia chi 5: %d (Ky vong: 100)", read_data);

        // Đọc lại địa chỉ 10
        #5;
        mem_address = 10;
        #5;
        if (read_data == 32'd255) 
            $display("[PASS] Doc dia chi 10: %d", read_data);
        else 
            $display("[FAIL] Doc dia chi 10: %d (Ky vong: 255)", read_data);

        // Đọc địa chỉ chưa ghi (mặc định 0 sau reset)
        #5;
        mem_address = 2;
        #5;
        if (read_data == 0) 
            $display("[PASS] Doc dia chi 2 (chua ghi): %d", read_data);
        else 
            $display("[FAIL] Doc dia chi 2: %d", read_data);

        $display("--- Ket thuc Test ---");
        $finish;
    end

endmodule

data_memory/data_memory/DataMemory_tb.vcd
$date
	Wed Dec 03 23:33:10 2025
$end
$version
	Icarus Verilog
$end
$timescale
	1ps
$end
$scope module DataMemory_tb $end
$var wire 32 ! read_data [31:0] $end
$var parameter 32 " DATA_WIDTH $end
$var parameter 32 # MEM_ADDR_WIDTH $end
$var reg 1 $ clk $end
$var reg 10 % mem_address [9:0] $end
$var reg 1 & mem_read_en $end
$var reg 1 ' mem_write_en $end
$var reg 1 ( reset $end
$var reg 32 ) write_data [31:0] $end
$scope module uut $end
$var wire 1 $ clk $end
$var wire 10 * mem_address [9:0] $end
$var wire 1 & mem_read_en $end
$var wire 1 ' mem_write_en $end
$var wire 1 ( reset $end
$var wire 32 + write_data [31:0] $end
$var parameter 32 , DATA_WIDTH $end
$var parameter 32 - MEM_ADDR_WIDTH $end
$var parameter 42 . MEM_SIZE $end
$var reg 32 / read_data [31:0] $end
$var integer 32 0 i [31:0] $end
$upscope $end
$upscope $end
$enddefinitions $end
$comment Show the parameter values. $end
$dumpall
b10000000000 .
b1010 -
b100000 ,
b1010 #
b100000 "
$end
#0
$dumpvars
bx 0
b0 /
b0 +
b0 *
b0 )
1(
0'
0&
b0 %
0$
b0 !
$end
#5000
b10000000000 0
1$
#10000
0$
#15000
1$
0(
#20000
0$
#25000
1$
1'
b1100100 )
b1100100 +
b101 %
b101 *
#30000
0$
#35000
1$
b11111111 )
b11111111 +
b1010 %
b1010 *
1'
#40000
0$
#45000
b1100100 !
b1100100 /
1$
1&
b101 %
b101 *
0'
#50000
0$
#55000
b11111111 !
b11111111 /
1$
b1010 %
b1010 *
#60000
0$
#65000
b0 !
b0 /
1$
b10 %
b10 *
